sslf/__init__.py
sslf/sslf.py
sslf-0.2.0.dist-info/LICENSE
sslf-0.2.0.dist-info/METADATA
sslf-0.2.0.dist-info/WHEEL
sslf-0.2.0.dist-info/top_level.txt
sslf-0.2.0.dist-info/RECORD
