Metadata-Version: 2.1
Name: sslf
Version: 0.2.0
Summary: A simple spectral line finder
Home-page: https://gitlab.com/chjordan/sslf
Author: Christopher H. Jordan
Author-email: christopherjordan87@gmail.com
License: MIT
Keywords: signal processing
Platform: UNKNOWN
Requires-Dist: numpy (>=1.8.0)
Requires-Dist: scipy
Requires-Dist: future
